{
  "kind": "NetworkNeighbors",
  "apiVersion": "spdx.softwarecomposition.kubescape.io/v1beta1",
  "metadata": {
    "name": "deployment-nginx",
    "uid": "ef88c2a8-288d-4bff-9292-151257806c52",
    "resourceVersion": "1",
    "creationTimestamp": "2024-04-18T12:20:14Z",
    "labels": {
      "kubescape.io/workload-api-group": "apps",
      "kubescape.io/workload-api-version": "v1",
      "kubescape.io/workload-kind": "Deployment",
      "kubescape.io/workload-name": "nginx"
    },
    "annotations": {
      "kubescape.io/completion": "complete",
      "kubescape.io/status": "ready"
    }
  },
  "spec": {
    "matchLabels": {
      "app": "nginx"
    },
    "ingress": [],
    "egress": [
      {
        "identifier": "e5e8ca3d76f701a19b7478fdc1c8c24ccc6cef9902b52c8c7e015439e2a1ddf3",
        "type": "internal",
        "dns": "",
        "dnsNames": null,
        "ports": [
          {
            "name": "UDP-53",
            "protocol": "UDP",
            "port": 53
          }
        ],
        "podSelector": {
          "matchLabels": {
            "k8s-app": "kube-dns"
          }
        },
        "namespaceSelector": {
          "matchLabels": {
            "kubernetes.io/metadata.name": "kube-system"
          }
        },
        "ipAddress": ""
      }
    ]
  }
}